tests/__init__.py
tests/test_model.py
tests/test_helpers.py
tests/test_loading.py
tests/test_settings.py
frigg_settings-3.1.2.dist-info/DESCRIPTION.rst
frigg_settings-3.1.2.dist-info/RECORD
frigg_settings-3.1.2.dist-info/WHEEL
frigg_settings-3.1.2.dist-info/metadata.json
frigg_settings-3.1.2.dist-info/METADATA
frigg_settings-3.1.2.dist-info/top_level.txt
frigg_settings/helpers.py
frigg_settings/__init__.py
frigg_settings/model.py
frigg_settings/settings.py
