Metadata-Version: 2.0
Name: frigg-settings
Version: 3.1.2
Summary: A module for parsing and discovery of frigg settings file
Home-page: https://github.com/frigg/frigg-settings
Author: The frigg team
Author-email: hi@frigg.io
License: MIT
Platform: UNKNOWN
Classifier: Programming Language :: Python :: 3
Requires-Dist: pyyaml (==3.11)
Requires-Dist: frigg-test-discovery (>1.0,<2.0)
